ran/__init__.py
ran/dt.py
ran/fs.py
ran/idmk.py
ran/mm.py
ran/pkg.py
ran-0.0.9.dist-info/METADATA
ran-0.0.9.dist-info/WHEEL
ran-0.0.9.dist-info/license
ran-0.0.9.dist-info/top_level.txt
ran-0.0.9.dist-info/RECORD
