Metadata-Version: 2.1
Name: ran
Version: 0.0.9
Summary: yet a library.
Home-page: https://github.com/chenshenchao/ran
Author: chenshenchao
Author-email: chenshenchao@outlook.com
License: MIT
Keywords: ran library
Platform: any
Classifier: License :: OSI Approved :: MIT License
Classifier: Intended Audience :: Developers
Classifier: Operating System :: OS Independent
Classifier: Programming Language :: Python :: 3
Classifier: Programming Language :: Python :: 3.7
Classifier: Programming Language :: Python :: 3.8
Classifier: Programming Language :: Python :: 3.9
